licensing/__init__.py
licensing/cli.py
licensing/crypto_utils.py
licensing/exceptions.py
licensing/hardware_fingerprint.py
licensing/license_generator.py
licensing/license_manager.py
licensing/preseed_generator.py
licensingpy-1.0.0.dist-info/LICENSE
licensingpy-1.0.0.dist-info/METADATA
licensingpy-1.0.0.dist-info/WHEEL
licensingpy-1.0.0.dist-info/entry_points.txt
licensingpy-1.0.0.dist-info/RECORD
