Metadata-Version: 2.3
Name: licensingpy
Version: 1.0.0
Summary: 🔐 Secure offline licensing system with beautiful CLI, ECDSA signatures, and hardware fingerprinting
License: MIT
Keywords: licensing,security,cryptography,ecdsa,hardware-fingerprinting,offline-licensing
Author: LicensingPy Team
Author-email: licensing@example.com
Requires-Python: >=3.8.1,<4.0.0
Classifier: Development Status :: 5 - Production/Stable
Classifier: Environment :: Console
Classifier: Intended Audience :: Developers
Classifier: Intended Audience :: Information Technology
Classifier: License :: OSI Approved :: MIT License
Classifier: Operating System :: OS Independent
Classifier: Programming Language :: Python :: 3
Classifier: Programming Language :: Python :: 3.9
Classifier: Programming Language :: Python :: 3.10
Classifier: Programming Language :: Python :: 3.11
Classifier: Programming Language :: Python :: 3.12
Classifier: Programming Language :: Python :: 3.13
Classifier: Programming Language :: Python :: 3.8
Classifier: Topic :: Security :: Cryptography
Classifier: Topic :: Software Development :: Libraries :: Python Modules
Classifier: Topic :: System :: Systems Administration
Classifier: Topic :: Utilities
Provides-Extra: all
Provides-Extra: hardware
Requires-Dist: click (>=8.0.0,<9.0.0)
Requires-Dist: netifaces (>=0.11.0,<0.12.0) ; extra == "hardware" or extra == "all"
Requires-Dist: psutil (>=5.9.0,<6.0.0) ; extra == "hardware" or extra == "all"
Requires-Dist: pycryptodome (>=3.19.0,<4.0.0)
Requires-Dist: rich (>=14.1.0,<15.0.0)
Project-URL: Bug Tracker, https://github.com/jiri-otoupal/LicensingPy/issues
Project-URL: Changelog, https://github.com/jiri-otoupal/LicensingPy/blob/main/CHANGELOG.md
Project-URL: Documentation, https://github.com/jiri-otoupal/LicensingPy
Project-URL: Funding, https://github.com/sponsors/jiri-otoupal
Project-URL: Homepage, https://github.com/jiri-otoupal/LicensingPy
Project-URL: Repository, https://github.com/jiri-otoupal/LicensingPy
